{
  "animation_count": 0,
  "armature_count": 0,
  "edge_count": 348,
  "file_identifier": "https://github.com/zhizi-moyu/for_modify/blob/main/output.stl",
  "file_size": 37216,
  "lamp_count": 1,
  "linked_files": [],
  "material_count": 0,
  "mesh_count": 1,
  "metadata": {
    "github_organization": "zhizi-moyu",
    "github_repo": "for_modify"
  },
  "missing_textures": {
    "count": 0,
    "file_path_to_color": {},
    "files": []
  },
  "object_count": 4,
  "poly_count": 232,
  "random_color": [
    0.8,
    0.8,
    0.8,
    1
  ],
  "save_uid": "output.stl",
  "scene_size": {
    "bbox_max": [
      60.0,
      15.0,
      54.0
    ],
    "bbox_min": [
      0.0,
      0.0,
      -9.992110252380371
    ]
  },
  "sha256": "4ad50b6e65e4963d34f2b85e15f96a86b204ae1ed64e816b0d5fd23b3e9b8432",
  "shape_key_count": 0,
  "vert_count": 120
}